kyutil/FTPUtils.py
kyutil/__init__.py
kyutil/ansible.py
kyutil/base.py
kyutil/base64_util.py
kyutil/build.py
kyutil/build_base.py
kyutil/build_ns8.py
kyutil/celery_util.py
kyutil/clean_disk.py
kyutil/cmd.py
kyutil/comps_ks.py
kyutil/config.py
kyutil/constant.py
kyutil/ctdy_koji.py
kyutil/data.py
kyutil/date_utils.py
kyutil/decorators.py
kyutil/download.py
kyutil/enums.py
kyutil/env.py
kyutil/excel.py
kyutil/exceptions.py
kyutil/file.py
kyutil/file_compare.py
kyutil/git_utils.py
kyutil/host.py
kyutil/hostinit.py
kyutil/html.py
kyutil/http_util.py
kyutil/inject_ks.py
kyutil/iso_check.py
kyutil/iso_utils.py
kyutil/koji_tools.py
kyutil/kyemail.py
kyutil/kyexcel.py
kyutil/lanxin.py
kyutil/log.py
kyutil/log_show_tools.py
kyutil/mash.py
kyutil/mock.py
kyutil/mq.py
kyutil/paths.py
kyutil/pungi_util.py
kyutil/reg_exp.py
kyutil/release_bugfix.py
kyutil/release_dependency.py
kyutil/repo.py
kyutil/repo_compare.py
kyutil/repo_utils.py
kyutil/repomd.py
kyutil/response_util.py
kyutil/rpm_compare.py
kyutil/rpm_operation.py
kyutil/rpms.py
kyutil/schedule.py
kyutil/sheeter.py
kyutil/shell.py
kyutil/signature.py
kyutil/source_pkg.py
kyutil/sso_login.py
kyutil/thread.py
kyutil/url.py
kyutil/util_repo_info.py
kyutil/util_rpm_info.py
kyutil/model/__init__.py
kyutil/model/vo/__init__.py
kyutil/model/vo/log_vo.py
kyutil-0.3.1.dist-info/METADATA
kyutil-0.3.1.dist-info/WHEEL
kyutil-0.3.1.dist-info/top_level.txt
kyutil-0.3.1.dist-info/RECORD
