Metadata-Version: 2.4
Name: kyutil
Version: 0.3.1
Summary: Python utils for kylin python application
Requires-Python: >=3.7
Requires-Dist: ansible-runner>=2.3.2
Requires-Dist: apscheduler>=3.10.4
Requires-Dist: beautifulsoup4>=4.13.5
Requires-Dist: celery>=5.2.7
Requires-Dist: configparser>=5.3.0
Requires-Dist: cryptography>=45.0.7
Requires-Dist: defusedxml>=0.7.1
Requires-Dist: dotenv>=0.9.9
Requires-Dist: fastapi>=0.103.2
Requires-Dist: gitpython>=3.1.45
Requires-Dist: kobo>=0.40.0
Requires-Dist: koji>=1.35.3
Requires-Dist: logzero>=1.7.0
Requires-Dist: lxml>=5.4.0
Requires-Dist: msgpack>=1.0.5
Requires-Dist: networkx>=2.6.3
Requires-Dist: numpy>=1.21.6
Requires-Dist: openpyxl>=3.1.3
Requires-Dist: packaging>=24.0
Requires-Dist: pandas>=1.1.5
Requires-Dist: paramiko>=3.5.1
Requires-Dist: pika>=1.3.2
Requires-Dist: playwright>=1.35.0
Requires-Dist: productmd>=1.48
Requires-Dist: pydantic>=2.5.3
Requires-Dist: pydot>=2.0.0
Requires-Dist: pytest>=7.4.4
Requires-Dist: python-jenkins>=1.8.3
Requires-Dist: pyyaml>=6.0.1
Requires-Dist: redis>=5.0.8
Requires-Dist: requests>=2.31.0
Requires-Dist: retry>=0.9.2
Requires-Dist: starlette>=0.27.0
Requires-Dist: urllib3>=2.0.7
Requires-Dist: wget>=3.2
Requires-Dist: xmltodict>=0.15.0
